Floppi_Music-0.1.dist-info/DESCRIPTION.rst
Floppi_Music-0.1.dist-info/METADATA
Floppi_Music-0.1.dist-info/RECORD
Floppi_Music-0.1.dist-info/WHEEL
Floppi_Music-0.1.dist-info/entry_points.txt
Floppi_Music-0.1.dist-info/metadata.json
Floppi_Music-0.1.dist-info/top_level.txt
floppi/__init__.py
floppi/cmds.py
floppi/config.py
floppi/drive.py
floppi/music.py
floppi/rpi.py
