Metadata-Version: 2.0
Name: Floppi-Music
Version: 0.1
Summary: Crazily advanced floppy music player for Raspberry Pi
Home-page: https://github.com/Natureshadow/floppi-music
Author: Dominik George
Author-email: nik@naturalnet.de
License: MirOS
Platform: UNKNOWN
Classifier: Development Status :: 5 - Production/Stable
Classifier: Environment :: Console
Classifier: Intended Audience :: Developers
Classifier: Intended Audience :: Science/Research
Classifier: License :: OSI Approved
Classifier: Operating System :: POSIX :: Linux
Classifier: Programming Language :: Python
Classifier: Topic :: Artistic Software
Classifier: Topic :: Multimedia :: Sound/Audio :: Players
Requires-Dist: RPi.GPIO
Requires-Dist: mmllib
